ug_gemeinde/Gemeinde.py
ug_gemeinde/Gemeinde.yaml
ug_gemeinde/GemeindeInstall.ps1
ug_gemeinde/GemeindeInstall.sh
ug_gemeinde/GemeindeStart.ps1
ug_gemeinde/GemeindeStart.sh
ug_gemeinde/GemeindeUpgrade.ps1
ug_gemeinde/GemeindeUpgrade.sh
ug_gemeinde/Gemeinde_Def.py
ug_gemeinde/Gemeinde_Modelle.py
ug_gemeinde/Icons.yaml
ug_gemeinde/Override.yaml
ug_gemeinde/__init__.py
ug_gemeinde-1.7.0.dist-info/METADATA
ug_gemeinde-1.7.0.dist-info/WHEEL
ug_gemeinde-1.7.0.dist-info/licenses/LICENSE
ug_gemeinde-1.7.0.dist-info/RECORD
