Metadata-Version: 2.4
Name: ug_gemeinde
Version: 1.7.0
Summary: Adressverwaltung für Gemeinden
License-File: LICENSE
Classifier: Development Status :: 5 - Production/Stable
Classifier: License :: OSI Approved :: MIT License
Classifier: Operating System :: OS Independent
Classifier: Programming Language :: Python :: 3
Requires-Python: >=3.10
Requires-Dist: pillow
Requires-Dist: psycopg2-binary
Requires-Dist: pyyaml
Requires-Dist: rich
Requires-Dist: ugbib-divers
Requires-Dist: ugbib-modell
Requires-Dist: ugbib-tkinter
Requires-Dist: ugbib-werkzeug
